{
    "updated": 1714471051,
    "posts": [
        {
            "id": "https://blog.eternalstorms.at/?p=4586",
            "title": "Transloader v3.1.6 for Mac, iPhone and iPad now available",
            "link": "https://blog.eternalstorms.at/2024/04/12/transloader-v3-1-6-for-mac-iphone-and-ipad-now-available/",
            "updated": 1712894211,
            "site_name": "Eternal Storms Software Blog"
        },
        {
            "id": "https://blog.eternalstorms.at/?p=4575",
            "title": "\u26a1\ufe0f Tameno v1.0.5 now available with more Mac goodness",
            "link": "https://blog.eternalstorms.at/2024/04/03/%e2%9a%a1%ef%b8%8f-tameno-v1-0-5-now-available-with-more-mac-goodness/",
            "updated": 1712105083,
            "site_name": "Eternal Storms Software Blog"
        },
        {
            "id": "https://blog.eternalstorms.at/?p=4546",
            "title": "\u26a1\ufe0f Tameno v1.0.3 available, with > 3400% more intervals, and \u201ccount to zero\u201d",
            "link": "https://blog.eternalstorms.at/2024/03/22/%e2%9a%a1%ef%b8%8f-tameno-v1-0-3-available-with-3400-more-intervals-and-count-to-zero/",
            "updated": 1711075048,
            "site_name": "Eternal Storms Software Blog"
        },
        {
            "id": "https://blog.eternalstorms.at/?p=4478",
            "title": "ScreenFloat v2.1.1 brings mouse and keyboard highlights to video recordings, and more",
            "link": "https://blog.eternalstorms.at/2024/03/13/screenfloat-v2-1-1-brings-mouse-and-keyboard-highlights-to-video-recordings-and-more/",
            "updated": 1710299107,
            "site_name": "Eternal Storms Software Blog"
        },
        {
            "id": "https://blog.eternalstorms.at/?p=4472",
            "title": "Check out ScreenCastsONLINE\u2019s epic ~43m coverage of ScreenFloat 2",
            "link": "https://blog.eternalstorms.at/2024/02/23/check-out-screencastsonlines-epic-43m-coverage-of-screenfloat-2/",
            "updated": 1708659758,
            "site_name": "Eternal Storms Software Blog"
        },
        {
            "id": "https://blog.eternalstorms.at/?p=4464",
            "title": "PSA: ScreenFloat 2\u2019s Trial Time Reset",
            "link": "https://blog.eternalstorms.at/2024/02/20/psa-screenfloat-2s-trial-time-reset/",
            "updated": 1708390372,
            "site_name": "Eternal Storms Software Blog"
        },
        {
            "id": "https://blog.eternalstorms.at/?p=4446",
            "title": "\u26a1\ufe0f [New Freeware App] Upsies \u2013 Upscale your images with MetalFX",
            "link": "https://blog.eternalstorms.at/2024/01/30/%e2%9a%a1%ef%b8%8f-new-app-upsies-upscale-your-images-with-metalfx-freeware/",
            "updated": 1706582978,
            "site_name": "Eternal Storms Software Blog"
        },
        {
            "id": "https://blog.eternalstorms.at/?p=4376",
            "title": "40 Years of Mac \u2013 Some Random Memories [Update 4]",
            "link": "https://blog.eternalstorms.at/2024/01/24/40-years-of-mac-random-memories/",
            "updated": 1706087986,
            "site_name": "Eternal Storms Software Blog"
        },
        {
            "id": "https://blog.eternalstorms.at/?p=4321",
            "title": "Get to Know ScreenFloat 2 \u2013 Part VIII: Shortcuts and Widgets",
            "link": "https://blog.eternalstorms.at/2024/01/17/get-to-know-screenfloat-2-part-viii-shortcuts-and-widgets/",
            "updated": 1705444704,
            "site_name": "Eternal Storms Software Blog"
        },
        {
            "id": "https://blog.eternalstorms.at/?p=4214",
            "title": "Get to Know ScreenFloat 2 \u2013 Part VII: iCloud Sync, Tag Browser, Spotlight",
            "link": "https://blog.eternalstorms.at/2024/01/17/get-to-know-screenfloat-2-part-vii-icloud-sync-tag-browser-spotlight/",
            "updated": 1705444695,
            "site_name": "Eternal Storms Software Blog"
        },
        {
            "id": "https://blog.eternalstorms.at/?p=4153",
            "title": "Get to Know ScreenFloat 2 \u2013 Part VI: Floating Shots\u2019 Double-Click Workflows",
            "link": "https://blog.eternalstorms.at/2024/01/17/get-to-know-screenfloat-2-part-vi-floating-shots-double-click-workflows/",
            "updated": 1705444689,
            "site_name": "Eternal Storms Software Blog"
        },
        {
            "id": "https://blog.eternalstorms.at/?p=3984",
            "title": "Get to Know ScreenFloat 2 \u2013 Part V: Editing, Markup, Annotations",
            "link": "https://blog.eternalstorms.at/2024/01/17/get-to-know-screenfloat-2-part-v-editing-markup-annotations/",
            "updated": 1705444682,
            "site_name": "Eternal Storms Software Blog"
        },
        {
            "id": "https://blog.eternalstorms.at/?p=3821",
            "title": "Get to Know ScreenFloat 2 \u2013 Part IV: The Shots Browser, Exporting, Printing",
            "link": "https://blog.eternalstorms.at/2024/01/17/get-to-know-screenfloat-2-part-iv-the-shots-browser-exporting-printing/",
            "updated": 1705444675,
            "site_name": "Eternal Storms Software Blog"
        },
        {
            "id": "https://blog.eternalstorms.at/?p=3801",
            "title": "Get to Know ScreenFloat 2 \u2013 Part III: Floating Shots, Color Picker, Visibility",
            "link": "https://blog.eternalstorms.at/2024/01/17/get-to-know-screenfloat-2-part-iii-floating-shots-color-picker-visibility/",
            "updated": 1705444659,
            "site_name": "Eternal Storms Software Blog"
        },
        {
            "id": "https://blog.eternalstorms.at/?p=3724",
            "title": "Get to Know ScreenFloat 2 \u2013 Part II: Take Screenshots and Record your Screen",
            "link": "https://blog.eternalstorms.at/2024/01/17/get-to-know-screenfloat-2-part-ii-take-screenshots-and-record-your-screen/",
            "updated": 1705444648,
            "site_name": "Eternal Storms Software Blog"
        },
        {
            "id": "https://blog.eternalstorms.at/?p=3352",
            "title": "Get to Know ScreenFloat 2 \u2013 Part I: An Overview",
            "link": "https://blog.eternalstorms.at/2024/01/17/get-to-know-screenfloat-2-part-i-an-overview/",
            "updated": 1705444553,
            "site_name": "Eternal Storms Software Blog"
        },
        {
            "id": "https://blog.eternalstorms.at/?p=3355",
            "title": "ScreenFloat 2.0 \u2013 Power up Your Screenshots",
            "link": "https://blog.eternalstorms.at/2024/01/17/screenfloat-2-power-up-your-screenshots/",
            "updated": 1705444502,
            "site_name": "Eternal Storms Software Blog"
        },
        {
            "id": "https://blog.eternalstorms.at/?p=4359",
            "title": "ScreenFloat 2. January 17, 2024. Something\u2019s up!",
            "link": "https://blog.eternalstorms.at/2024/01/10/screenfloat-2-january-17-2024-somethings-up/",
            "updated": 1704848923,
            "site_name": "Eternal Storms Software Blog"
        },
        {
            "id": "https://blog.eternalstorms.at/?p=3348",
            "title": "\u26a1\ufe0f Transloader is ~40% off for its 11-year anniversary!",
            "link": "https://blog.eternalstorms.at/2023/11/27/%e2%9a%a1%ef%b8%8f-transloader-is-40-off-for-its-11-year-anniversary/",
            "updated": 1701056548,
            "site_name": "Eternal Storms Software Blog"
        },
        {
            "id": "https://blog.eternalstorms.at/?p=3341",
            "title": "Transloader v3.1.5 now available",
            "link": "https://blog.eternalstorms.at/2023/11/23/transloader-v3-1-5-now-available/",
            "updated": 1700708532,
            "site_name": "Eternal Storms Software Blog"
        },
        {
            "id": "https://blog.eternalstorms.at/?p=3332",
            "title": "Tameno on ProductHunt",
            "link": "https://blog.eternalstorms.at/2023/10/19/tameno-on-producthunt/",
            "updated": 1697700987,
            "site_name": "Eternal Storms Software Blog"
        },
        {
            "id": "https://blog.eternalstorms.at/?p=3285",
            "title": "Using a Mid-2012 MacBook Pro with macOS 13 Ventura for iCloud Sync Testing & Debugging",
            "link": "https://blog.eternalstorms.at/2023/09/21/using-a-mid-2012-macbook-pro-with-macos-13-ventura-for-icloud-sync-testing-debugging/",
            "updated": 1695268571,
            "site_name": "Eternal Storms Software Blog"
        },
        {
            "id": "https://blog.eternalstorms.at/?p=3282",
            "title": "Tameno v1.0.1 fixes a bug on Apple Watch with watchOS 10",
            "link": "https://blog.eternalstorms.at/2023/09/20/tameno-v1-0-1-fixes-a-bug-on-apple-watch-with-watchos-10/",
            "updated": 1695201610,
            "site_name": "Eternal Storms Software Blog"
        },
        {
            "id": "https://blog.eternalstorms.at/?p=3262",
            "title": "Introducing \u201cTameno \u2013 Get Tapped\u201d, for Apple Watch, iPhone, iPad, Mac and Apple TV",
            "link": "https://blog.eternalstorms.at/2023/09/18/introducing-tameno-get-tapped-for-apple-watch-iphone-ipad-mac-and-apple-tv/",
            "updated": 1695031200,
            "site_name": "Eternal Storms Software Blog"
        },
        {
            "id": "https://blog.eternalstorms.at/?p=3255",
            "title": "It\u2019s Yoink for Mac\u2019s 12-year anniversary! (Sale!)",
            "link": "https://blog.eternalstorms.at/2023/09/01/its-yoink-for-macs-12-year-anniversary-sale/",
            "updated": 1693530271,
            "site_name": "Eternal Storms Software Blog"
        },
        {
            "id": "https://blog.eternalstorms.at/?p=3246",
            "title": "Xcode\u2019s popup documentation tied to compiler",
            "link": "https://blog.eternalstorms.at/2023/08/25/xcodes-popup-documentation-tied-to-compiler/",
            "updated": 1692933117,
            "site_name": "Eternal Storms Software Blog"
        },
        {
            "id": "https://blog.eternalstorms.at/?p=3239",
            "title": "On Transloader for Mac costing money",
            "link": "https://blog.eternalstorms.at/2023/08/23/on-transloader-for-mac-costing-money/",
            "updated": 1692775217,
            "site_name": "Eternal Storms Software Blog"
        },
        {
            "id": "https://blog.eternalstorms.at/?p=3231",
            "title": "iPhone 15 Color Rumors be like\u2026",
            "link": "https://blog.eternalstorms.at/2023/08/22/iphone-15-color-rumors-be-like/",
            "updated": 1692688484,
            "site_name": "Eternal Storms Software Blog"
        },
        {
            "id": "https://blog.eternalstorms.at/?p=3220",
            "title": "Calling all heavy-duty ScreenFloat users!",
            "link": "https://blog.eternalstorms.at/2023/06/26/calling-all-heavy-duty-screenfloat-users/",
            "updated": 1687741271,
            "site_name": "Eternal Storms Software Blog"
        },
        {
            "id": "https://blog.eternalstorms.at/?p=3150",
            "title": "AirPods Max \u2013 A short, personal review",
            "link": "https://blog.eternalstorms.at/2023/04/19/airpods-max-a-short-personal-review/",
            "updated": 1681866250,
            "site_name": "Eternal Storms Software Blog"
        },
        {
            "id": "https://blog.eternalstorms.at/?p=3142",
            "title": "SiriMote v1.4.5 (Freeware) now available",
            "link": "https://blog.eternalstorms.at/2023/02/03/sirimote-v1-4-5-freeware-now-available/",
            "updated": 1675401927,
            "site_name": "Eternal Storms Software Blog"
        },
        {
            "id": "https://blog.eternalstorms.at/?p=3125",
            "title": "Switching on iCloud Photos",
            "link": "https://blog.eternalstorms.at/2023/01/25/switching-on-icloud-photos/",
            "updated": 1674629678,
            "site_name": "Eternal Storms Software Blog"
        },
        {
            "id": "https://blog.eternalstorms.at/?p=3122",
            "title": "PSA: Get Setapp, 1Password and MasterClass at up to 40% off",
            "link": "https://blog.eternalstorms.at/2022/12/21/psa-get-setapp-1password-and-masterclass-at-up-to-40-off/",
            "updated": 1671605753,
            "site_name": "Eternal Storms Software Blog"
        },
        {
            "id": "https://blog.eternalstorms.at/?p=3108",
            "title": "Black Friday 2022 \u2013 Eternal Storms Software App Sale",
            "link": "https://blog.eternalstorms.at/2022/11/25/black-friday-2022-eternal-storms-software-app-sale/",
            "updated": 1669337673,
            "site_name": "Eternal Storms Software Blog"
        },
        {
            "id": "https://blog.eternalstorms.at/?p=3094",
            "title": "How to: Always allow pastes for Yoink\u2019s Clipboard Monitor on iOS 16.1 and newer",
            "link": "https://blog.eternalstorms.at/2022/11/14/how-to-always-allow-pastes-for-yoinks-clipboard-monitor-on-ios-16-1-and-newer/",
            "updated": 1668392342,
            "site_name": "Eternal Storms Software Blog"
        },
        {
            "id": "https://blog.eternalstorms.at/?p=3088",
            "title": "PSA: macOS Ventura 3rd-Party Widget Configuration Broken [Update 2: fixed in macOS 13.2]",
            "link": "https://blog.eternalstorms.at/2022/11/10/psa-macos-ventura-3rd-party-widget-configuration-broken/",
            "updated": 1668062673,
            "site_name": "Eternal Storms Software Blog"
        },
        {
            "id": "https://blog.eternalstorms.at/?p=3030",
            "title": "Introducing Citator for iPhone and iPad \u2013 Store, Cherish and Share Memorable Quotes",
            "link": "https://blog.eternalstorms.at/2022/09/12/introducing-citator-for-iphone-and-ipad/",
            "updated": 1662977360,
            "site_name": "Eternal Storms Software Blog"
        },
        {
            "id": "https://blog.eternalstorms.at/?p=2966",
            "title": "Review: BenQ\u2019s ScreenBar",
            "link": "https://blog.eternalstorms.at/2022/07/26/review-benqs-screenbar/",
            "updated": 1658802075,
            "site_name": "Eternal Storms Software Blog"
        },
        {
            "id": "https://blog.eternalstorms.at/?p=2961",
            "title": "Transloader for Mac, iPad and iPhone & Yoink for iPad and iPhone updated",
            "link": "https://blog.eternalstorms.at/2022/06/17/transloader-for-mac-ipad-and-iphone-yoink-for-ipad-and-iphone-updated/",
            "updated": 1655449197,
            "site_name": "Eternal Storms Software Blog"
        },
        {
            "id": "https://blog.eternalstorms.at/?p=2898",
            "title": "[Development Journal: ScreenFloat 2] Entry 4 \u2013 Roadblock: Deadlock",
            "link": "https://blog.eternalstorms.at/2022/06/17/development-journal-screenfloat-2-entry-4-roadblock-deadlock/",
            "updated": 1655447769,
            "site_name": "Eternal Storms Software Blog"
        },
        {
            "id": "https://blog.eternalstorms.at/?p=2807",
            "title": "[Development Journal: ScreenFloat 2] Entry 3 \u2013 Busy Doing Nothing*",
            "link": "https://blog.eternalstorms.at/2022/04/29/development-journal-screenfloat-2-entry-3-busy-doing-nothing/",
            "updated": 1651210158,
            "site_name": "Eternal Storms Software Blog"
        },
        {
            "id": "https://blog.eternalstorms.at/?p=2754",
            "title": "[Development Journal: ScreenFloat 2] Entry 2 \u2013 Core Data",
            "link": "https://blog.eternalstorms.at/2022/04/15/development-journal-screenfloat-2-entry-2-core-data/",
            "updated": 1649993955,
            "site_name": "Eternal Storms Software Blog"
        },
        {
            "id": "https://blog.eternalstorms.at/?p=2748",
            "title": "Transloader v3.1.1 is now available for Mac, iPad and iPhone",
            "link": "https://blog.eternalstorms.at/2022/04/11/transloader-v3-1-1-is-now-available-for-mac-ipad-and-iphone/",
            "updated": 1649633471,
            "site_name": "Eternal Storms Software Blog"
        },
        {
            "id": "https://blog.eternalstorms.at/?p=2702",
            "title": "[Development Journal: ScreenFloat 2] Entry 1 \u2013 Fundamental Decisions",
            "link": "https://blog.eternalstorms.at/2022/04/08/development-journal-screenfloat-2-entry-1-fundamental-decisions/",
            "updated": 1649387598,
            "site_name": "Eternal Storms Software Blog"
        },
        {
            "id": "https://blog.eternalstorms.at/?p=2683",
            "title": "Yoink for iPad and iPhone v2.4.1 now available",
            "link": "https://blog.eternalstorms.at/2022/04/04/yoink-for-ipad-and-iphone-v2-4-1-now-available/",
            "updated": 1649039098,
            "site_name": "Eternal Storms Software Blog"
        },
        {
            "id": "https://blog.eternalstorms.at/?p=2648",
            "title": "PSA: *Get* and *stay* organized: with DEVONthink and Yoink for Mac \u2013 at 20% off",
            "link": "https://blog.eternalstorms.at/2022/03/30/devonthink-yoink-cross-promo-20perc-off/",
            "updated": 1648603211,
            "site_name": "Eternal Storms Software Blog"
        },
        {
            "id": "https://blog.eternalstorms.at/?p=2641",
            "title": "Yoink v3.6.8 for Mac now available",
            "link": "https://blog.eternalstorms.at/2022/03/07/yoink-v3-6-8-for-mac-now-available/",
            "updated": 1646618208,
            "site_name": "Eternal Storms Software Blog"
        },
        {
            "id": "https://blog.eternalstorms.at/?p=2627",
            "title": "Yoink\u2019s Clipboard History and Your Privacy",
            "link": "https://blog.eternalstorms.at/2022/02/22/yoinks-clipboard-history-and-your-privacy/",
            "updated": 1645498738,
            "site_name": "Eternal Storms Software Blog"
        },
        {
            "id": "https://blog.eternalstorms.at/?p=2586",
            "title": "Notes on the Implementation of Yoink for Mac\u2019s Revamped Clipboard History SwiftUI Widget",
            "link": "https://blog.eternalstorms.at/2022/02/21/notes-on-the-implementation-of-yoink-for-macs-revamped-clipboard-history-swiftui-widget/",
            "updated": 1645404383,
            "site_name": "Eternal Storms Software Blog"
        },
        {
            "id": "https://blog.eternalstorms.at/?p=2558",
            "title": "Yoink for Mac v3.6.5 (finally) re-introduces its Clipboard History and Widget",
            "link": "https://blog.eternalstorms.at/2022/02/21/yoink-for-mac-v3-6-5/",
            "updated": 1645404366,
            "site_name": "Eternal Storms Software Blog"
        },
        {
            "id": "https://blog.eternalstorms.at/?p=2614",
            "title": "[macOS Developer Tip] Audio that respects macOS\u2019 \u201cPlay user interface sound effects\u201d setting",
            "link": "https://blog.eternalstorms.at/2022/02/18/macos-developer-tip-play-audio-that-respects-macos-user-interface-sound-effects-setting/",
            "updated": 1645167534,
            "site_name": "Eternal Storms Software Blog"
        },
        {
            "id": "https://blog.eternalstorms.at/?p=2544",
            "title": "BackLog v1.0.1",
            "link": "https://blog.eternalstorms.at/2022/01/26/backlog-v1-0-1/",
            "updated": 1643164937,
            "site_name": "Eternal Storms Software Blog"
        },
        {
            "id": "https://blog.eternalstorms.at/?p=2522",
            "title": "Introducing BackLog \u2013 a Freeware Developer Tool for Mac",
            "link": "https://blog.eternalstorms.at/2022/01/18/introducing-backlog-a-freeware-developer-tool-for-mac/",
            "updated": 1642491869,
            "site_name": "Eternal Storms Software Blog"
        },
        {
            "id": "https://blog.eternalstorms.at/?p=2517",
            "title": "SiriMote v1.4.4",
            "link": "https://blog.eternalstorms.at/2022/01/07/sirimote-v1-4-4/",
            "updated": 1641527668,
            "site_name": "Eternal Storms Software Blog"
        },
        {
            "id": "https://blog.eternalstorms.at/?p=2475",
            "title": "New Mac, New Setup",
            "link": "https://blog.eternalstorms.at/2022/01/04/new-mac-new-setup/",
            "updated": 1641283558,
            "site_name": "Eternal Storms Software Blog"
        },
        {
            "id": "https://blog.eternalstorms.at/?p=2450",
            "title": "Developer Tip: An XPC service\u2019s methods aren\u2019t necessarily run on the main thread",
            "link": "https://blog.eternalstorms.at/2021/10/14/developer-tip-an-xpc-services-methods-arent-necessarily-run-on-the-main-thread/",
            "updated": 1634174608,
            "site_name": "Eternal Storms Software Blog"
        },
        {
            "id": "https://blog.eternalstorms.at/?p=2434",
            "title": "Yoink for iPad and iPhone v2.4 \u2013 Improved Background Clipboard Monitoring",
            "link": "https://blog.eternalstorms.at/2021/10/07/yoink-for-ipad-and-iphone-v2-4-improved-background-clipboard-monitoring/",
            "updated": 1633566450,
            "site_name": "Eternal Storms Software Blog"
        },
        {
            "id": "https://blog.eternalstorms.at/?p=2417",
            "title": "Yoink for iPad and iPhone v2.3.5 \u2013 Background Clipboard Monitoring",
            "link": "https://blog.eternalstorms.at/2021/09/29/yoink-for-ipad-and-iphone-v2-3-5-background-clipboard-monitoring/",
            "updated": 1632873014,
            "site_name": "Eternal Storms Software Blog"
        },
        {
            "id": "https://blog.eternalstorms.at/?p=2397",
            "title": "Yoink v2.3 for iPad and iPhone is ready for iOS 15",
            "link": "https://blog.eternalstorms.at/2021/09/20/yoink-v2-3-ios-15/",
            "updated": 1632130184,
            "site_name": "Eternal Storms Software Blog"
        },
        {
            "id": "https://blog.eternalstorms.at/?p=2378",
            "title": "Yoink for Mac\u2019s 10-Year Anniversary",
            "link": "https://blog.eternalstorms.at/2021/09/01/yoink-for-macs-10-year-anniversary/",
            "updated": 1630470462,
            "site_name": "Eternal Storms Software Blog"
        },
        {
            "id": "https://blog.eternalstorms.at/?p=2368",
            "title": "Maintenance updates for Yoink and Transloader",
            "link": "https://blog.eternalstorms.at/2021/08/10/maintenance-updates-for-yoink-and-transloader/",
            "updated": 1628557380,
            "site_name": "Eternal Storms Software Blog"
        },
        {
            "id": "https://blog.eternalstorms.at/?p=2362",
            "title": "Transloader 3 now available on Setapp",
            "link": "https://blog.eternalstorms.at/2021/07/08/transloader-3-now-available-on-setapp/",
            "updated": 1625727953,
            "site_name": "Eternal Storms Software Blog"
        },
        {
            "id": "https://blog.eternalstorms.at/?p=2055",
            "title": "Increase Transloader\u2019s Download-Powers \u2013 with Downie!",
            "link": "https://blog.eternalstorms.at/2021/07/05/increase-transloaders-download-powers-with-downie/",
            "updated": 1625464850,
            "site_name": "Eternal Storms Software Blog"
        },
        {
            "id": "https://blog.eternalstorms.at/?p=2353",
            "title": "Open Source: Draw Siri Remotes (2015-2021) in code",
            "link": "https://blog.eternalstorms.at/2021/07/02/open-source-draw-siri-remotes-2015-2021-in-code/",
            "updated": 1625196614,
            "site_name": "Eternal Storms Software Blog"
        },
        {
            "id": "https://blog.eternalstorms.at/?p=2301",
            "title": "Get to know Transloader 3 \u2013 Part VII: File Actions",
            "link": "https://blog.eternalstorms.at/2021/07/01/get-to-know-transloader-3-part-vii-file-actions/",
            "updated": 1625109138,
            "site_name": "Eternal Storms Software Blog"
        },
        {
            "id": "https://blog.eternalstorms.at/?p=2304",
            "title": "SiriMote 1.4 now supports Apple TV Siri Remote (2021)",
            "link": "https://blog.eternalstorms.at/2021/06/30/sirimote-1-4-now-supports-apple-tv-siri-remote-2021/",
            "updated": 1625035343,
            "site_name": "Eternal Storms Software Blog"
        },
        {
            "id": "https://blog.eternalstorms.at/?p=2258",
            "title": "Get to know Transloader 3 \u2013 Part VI: Link Actions",
            "link": "https://blog.eternalstorms.at/2021/06/29/get-to-know-transloader-3-part-vi-link-actions/",
            "updated": 1624951949,
            "site_name": "Eternal Storms Software Blog"
        },
        {
            "id": "https://blog.eternalstorms.at/?p=2215",
            "title": "Get to know Transloader 3 \u2013 Part V: Login to Download",
            "link": "https://blog.eternalstorms.at/2021/06/28/get-to-know-transloader-3-part-v-login-to-download/",
            "updated": 1624847419,
            "site_name": "Eternal Storms Software Blog"
        },
        {
            "id": "https://blog.eternalstorms.at/?p=2183",
            "title": "Get to know Transloader 3 \u2013 Part IV: Preferences and Settings",
            "link": "https://blog.eternalstorms.at/2021/06/25/get-to-know-transloader-3-part-iv-preferences-and-settings/",
            "updated": 1624603221,
            "site_name": "Eternal Storms Software Blog"
        },
        {
            "id": "https://blog.eternalstorms.at/?p=2160",
            "title": "Get to know Transloader 3 \u2013 Part III: Siri Shortcuts on iPhone and iPad",
            "link": "https://blog.eternalstorms.at/2021/06/24/get-to-know-transloader-3-part-iii-siri-shortcuts-on-iphone-and-ipad/",
            "updated": 1624507369,
            "site_name": "Eternal Storms Software Blog"
        },
        {
            "id": "https://blog.eternalstorms.at/?p=2115",
            "title": "Get to know Transloader 3 \u2013 Part II: Dive Into Transloader\u2019s iOS app",
            "link": "https://blog.eternalstorms.at/2021/06/23/get-to-know-transloader-3-part-ii-dive-into-transloaders-ios-app/",
            "updated": 1624426265,
            "site_name": "Eternal Storms Software Blog"
        },
        {
            "id": "https://blog.eternalstorms.at/?p=2066",
            "title": "Get to know Transloader 3 \u2013 Part I: Starting Downloads Remotely on Macs",
            "link": "https://blog.eternalstorms.at/2021/06/22/get-to-know-transloader-3-part-i-starting-downloads-remotely-on-macs/",
            "updated": 1624340407,
            "site_name": "Eternal Storms Software Blog"
        },
        {
            "id": "https://blog.eternalstorms.at/?p=2033",
            "title": "Transloader 3 \u2013 Start downloads on your Macs, remotely from your iPhone, iPad, or other Macs",
            "link": "https://blog.eternalstorms.at/2021/06/07/transloader-3-released/",
            "updated": 1623022299,
            "site_name": "Eternal Storms Software Blog"
        },
        {
            "id": "https://blog.eternalstorms.at/?p=2024",
            "title": "Mac Developer Tip: How to get Remote Notifications Working Again (If They Suddenly Aren\u2019t)",
            "link": "https://blog.eternalstorms.at/2021/03/31/mac-developer-tip-how-to-get-remote-notifications-working-again-if-they-suddenly-arent/",
            "updated": 1617174453,
            "site_name": "Eternal Storms Software Blog"
        },
        {
            "id": "https://blog.eternalstorms.at/?p=2013",
            "title": "Open Source [macOS] \u2013 NSMenuItems with Subtitles",
            "link": "https://blog.eternalstorms.at/2021/03/13/ess-nsmenuitems-with-subtitles/",
            "updated": 1615607383,
            "site_name": "Eternal Storms Software Blog"
        },
        {
            "id": "https://blog.eternalstorms.at/?p=2002",
            "title": "Apple announces App Store Small Business Program",
            "link": "https://blog.eternalstorms.at/2020/11/18/apple-announces-app-store-small-business-program/",
            "updated": 1605674678,
            "site_name": "Eternal Storms Software Blog"
        },
        {
            "id": "https://blog.eternalstorms.at/?p=1995",
            "title": "App Update Galore (macOS Big Sur & Apple Silicon)",
            "link": "https://blog.eternalstorms.at/2020/11/09/app-update-galore/",
            "updated": 1604893860,
            "site_name": "Eternal Storms Software Blog"
        },
        {
            "id": "https://blog.eternalstorms.at/?p=1981",
            "title": "Interview on Indie Dev Mondays",
            "link": "https://blog.eternalstorms.at/2020/10/27/interview-on-indie-dev-mondays/",
            "updated": 1603759155,
            "site_name": "Eternal Storms Software Blog"
        },
        {
            "id": "https://blog.eternalstorms.at/?p=1968",
            "title": "Interesting Watch: Donkey Kong Country 25th Anniversary Documentary",
            "link": "https://blog.eternalstorms.at/2020/10/26/interesting-watch-donkey-kong-country-25th-anniversary-documentary/",
            "updated": 1603674000,
            "site_name": "Eternal Storms Software Blog"
        },
        {
            "id": "https://blog.eternalstorms.at/?p=1975",
            "title": "A foggy day in Vienna",
            "link": "https://blog.eternalstorms.at/2020/10/23/a-foggy-day-in-vienna/",
            "updated": 1603413932,
            "site_name": "Eternal Storms Software Blog"
        },
        {
            "id": "https://blog.eternalstorms.at/?p=1961",
            "title": "Interesting Read: We Hacked Apple for 3 Months",
            "link": "https://blog.eternalstorms.at/2020/10/19/interesting-read-we-hacked-apple-for-3-months/",
            "updated": 1603068067,
            "site_name": "Eternal Storms Software Blog"
        },
        {
            "id": "https://blog.eternalstorms.at/?p=1946",
            "title": "Use Yoink on iPad in Slide-Over or Split View",
            "link": "https://blog.eternalstorms.at/2020/10/17/use-yoink-on-ipad-in-slide-over-or-split-view/",
            "updated": 1602900963,
            "site_name": "Eternal Storms Software Blog"
        },
        {
            "id": "https://blog.eternalstorms.at/?p=1873",
            "title": "How to Save or Download files directly into Yoink for Mac",
            "link": "https://blog.eternalstorms.at/2020/10/13/how-to-save-or-download-files-directly-into-yoink-for-mac/",
            "updated": 1602571523,
            "site_name": "Eternal Storms Software Blog"
        },
        {
            "id": "https://blog.eternalstorms.at/?p=1834",
            "title": "Yoink for iPad and iPhone\u2019s 3 Year Anniversary",
            "link": "https://blog.eternalstorms.at/2020/10/12/yoink-for-ipad-and-iphones-3-year-anniversary/",
            "updated": 1602467722,
            "site_name": "Eternal Storms Software Blog"
        },
        {
            "id": "https://blog.eternalstorms.at/?p=1807",
            "title": "My Apps, macOS Big Sur, and Apple Silicon",
            "link": "https://blog.eternalstorms.at/2020/10/06/my-apps-macos-big-sur-and-apple-silicon/",
            "updated": 1601964924,
            "site_name": "Eternal Storms Software Blog"
        },
        {
            "id": "https://blog.eternalstorms.at/?p=1800",
            "title": "SiriMote v1.3.9 now available",
            "link": "https://blog.eternalstorms.at/2020/10/05/sirimote-v1-3-9-now-available/",
            "updated": 1601854997,
            "site_name": "Eternal Storms Software Blog"
        },
        {
            "id": "https://blog.eternalstorms.at/?p=1789",
            "title": "Big Sur\u2019s new Preferences Toolbar",
            "link": "https://blog.eternalstorms.at/2020/09/24/big-surs-new-preferences-toolbar/",
            "updated": 1600905270,
            "site_name": "Eternal Storms Software Blog"
        },
        {
            "id": "https://blog.eternalstorms.at/?p=1770",
            "title": "My Update-Cycles",
            "link": "https://blog.eternalstorms.at/2020/09/15/my-update-cycles/",
            "updated": 1600144143,
            "site_name": "Eternal Storms Software Blog"
        },
        {
            "id": "https://blog.eternalstorms.at/?p=1759",
            "title": "Yoink\u2019s Clipboard Usage on iPad and iPhone",
            "link": "https://blog.eternalstorms.at/2020/07/07/yoinks-clipboard-usage-on-ipad-and-iphone/",
            "updated": 1594093732,
            "site_name": "Eternal Storms Software Blog"
        },
        {
            "id": "https://blog.eternalstorms.at/?p=1749",
            "title": "Extended Trial Times for Yoink and ScreenFloat for Mac",
            "link": "https://blog.eternalstorms.at/2020/03/28/extended-trial-times-for-yoink-and-screenfloat-for-mac/",
            "updated": 1585373612,
            "site_name": "Eternal Storms Software Blog"
        },
        {
            "id": "https://blog.eternalstorms.at/?p=1730",
            "title": "ScreenFloat v1.5.16 on macOS 10.15 Catalina",
            "link": "https://blog.eternalstorms.at/2019/10/11/screenfloat-v1-5-16-on-macos-10-15-catalina/",
            "updated": 1570771476,
            "site_name": "Eternal Storms Software Blog"
        },
        {
            "id": "https://blog.eternalstorms.at/?p=1716",
            "title": "Yoink for Mac v3.5.5 now available",
            "link": "https://blog.eternalstorms.at/2019/07/02/yoink-for-mac-v3-5-5-now-available/",
            "updated": 1562035881,
            "site_name": "Eternal Storms Software Blog"
        },
        {
            "id": "https://blog.eternalstorms.at/?p=1712",
            "title": "Interview of yours truly by Sahil Parikh",
            "link": "https://blog.eternalstorms.at/2019/06/03/interview-of-yours-truly-by-sahil-parikh/",
            "updated": 1559533199,
            "site_name": "Eternal Storms Software Blog"
        },
        {
            "id": "https://blog.eternalstorms.at/?p=1695",
            "title": "Yoink v3.5.3 for Mac now available",
            "link": "https://blog.eternalstorms.at/2019/04/22/yoink-v3-5-3-for-mac-now-available/",
            "updated": 1555861715,
            "site_name": "Eternal Storms Software Blog"
        },
        {
            "id": "https://blog.eternalstorms.at/?p=1698",
            "title": "Yoink for iOS Featured on the App Store",
            "link": "https://blog.eternalstorms.at/2019/04/19/yoink-for-ios-featured-on-the-app-store/",
            "updated": 1555666176,
            "site_name": "Eternal Storms Software Blog"
        },
        {
            "id": "https://blog.eternalstorms.at/?p=1686",
            "title": "Show and Tell: Disk Sensei by Oskar Groth",
            "link": "https://blog.eternalstorms.at/2019/04/19/show-and-tell-disk-sensei-by-oskar-groth/",
            "updated": 1555643667,
            "site_name": "Eternal Storms Software Blog"
        },
        {
            "id": "https://blog.eternalstorms.at/?p=1674",
            "title": "Show and Tell: Amusic by Michael Buss Andersen",
            "link": "https://blog.eternalstorms.at/2019/04/18/show-and-tell-amusic-by-michael-buss-andersen/",
            "updated": 1555546558,
            "site_name": "Eternal Storms Software Blog"
        },
        {
            "id": "https://blog.eternalstorms.at/?p=1645",
            "title": "New Blog Series: Show and Tell",
            "link": "https://blog.eternalstorms.at/2019/03/15/show-and-tell-submit/",
            "updated": 1552635483,
            "site_name": "Eternal Storms Software Blog"
        },
        {
            "id": "https://blog.eternalstorms.at/?p=1622",
            "title": "Side Project: Promo Codes (Part 1 \u2013 Intro and Promo Code Creation)",
            "link": "https://blog.eternalstorms.at/2019/02/19/promocodespart1/",
            "updated": 1550563025,
            "site_name": "Eternal Storms Software Blog"
        },
        {
            "id": "https://blog.eternalstorms.at/?p=1616",
            "title": "Yoink v2.0.1 for iPad and iPhone now available",
            "link": "https://blog.eternalstorms.at/2019/01/28/yoinkv201/",
            "updated": 1548644769,
            "site_name": "Eternal Storms Software Blog"
        },
        {
            "id": "https://blog.eternalstorms.at/?p=1607",
            "title": "\u26a1\ufe0f Black Friday 2018 \u2013 Sale",
            "link": "https://blog.eternalstorms.at/2018/11/23/%e2%9a%a1%ef%b8%8f-black-friday-2018-sale/",
            "updated": 1542959255,
            "site_name": "Eternal Storms Software Blog"
        },
        {
            "id": "https://blog.eternalstorms.at/?p=1596",
            "title": "Yoink v3.5.2 for Mac now available",
            "link": "https://blog.eternalstorms.at/2018/11/12/yoink-v3-5-2-for-mac-now-available/",
            "updated": 1541993724,
            "site_name": "Eternal Storms Software Blog"
        },
        {
            "id": "https://blog.eternalstorms.at/?p=1588",
            "title": "Developer Tip: Custom Icons for Quick Actions",
            "link": "https://blog.eternalstorms.at/2018/10/19/developer-tip-custom-icons-for-quick-actions/",
            "updated": 1539932704,
            "site_name": "Eternal Storms Software Blog"
        },
        {
            "id": "https://blog.eternalstorms.at/?p=1567",
            "title": "Developer Tip: Today Widgets and macOS Mojave\u2019s Dark Mode",
            "link": "https://blog.eternalstorms.at/2018/09/25/developer-tip-today-widgets-and-macos-mojaves-dark-mode/",
            "updated": 1537835337,
            "site_name": "Eternal Storms Software Blog"
        },
        {
            "id": "https://blog.eternalstorms.at/?p=1556",
            "title": "Yoink v3.5 for Mac \u2013 Handoff and Clipboard History",
            "link": "https://blog.eternalstorms.at/2018/09/24/yoink-v3-5/",
            "updated": 1537767345,
            "site_name": "Eternal Storms Software Blog"
        },
        {
            "id": "https://blog.eternalstorms.at/?p=1528",
            "title": "Yoink 2.0 for iPad and iPhone \u2013 iCloud Sync, Handoff, Siri Shortcuts and much more",
            "link": "https://blog.eternalstorms.at/2018/09/21/yoink-2-0/",
            "updated": 1537524207,
            "site_name": "Eternal Storms Software Blog"
        },
        {
            "id": "https://blog.eternalstorms.at/?p=1514",
            "title": "Maintenance-Updates for Yoink for Mac and ScreenFloat",
            "link": "https://blog.eternalstorms.at/2018/05/22/maintenance-updates-for-yoink-for-mac-and-screenfloat/",
            "updated": 1526955299,
            "site_name": "Eternal Storms Software Blog"
        },
        {
            "id": "https://blog.eternalstorms.at/?p=1505",
            "title": "flickery v1.9.45 with critical bug fixes now available",
            "link": "https://blog.eternalstorms.at/2018/05/02/flickery-v1-9-45-with-critical-bug-fixes-now-available/",
            "updated": 1525220663,
            "site_name": "Eternal Storms Software Blog"
        },
        {
            "id": "https://blog.eternalstorms.at/?p=1499",
            "title": "How-To: \u2018Gray out\u2019 Files in Finder",
            "link": "https://blog.eternalstorms.at/2018/04/11/how-to-gray-out-files-in-finder/",
            "updated": 1523412916,
            "site_name": "Eternal Storms Software Blog"
        },
        {
            "id": "https://blog.eternalstorms.at/?p=1490",
            "title": "ScreenFloat v1.5.14 released \u2013 Maintenance Update",
            "link": "https://blog.eternalstorms.at/2018/03/16/screenfloat-v1-5-14-released-maintenance-update/",
            "updated": 1521173466,
            "site_name": "Eternal Storms Software Blog"
        },
        {
            "id": "https://blog.eternalstorms.at/?p=1478",
            "title": "Yoink for Mac and iOS \u2013 Updates",
            "link": "https://blog.eternalstorms.at/2018/03/13/yoink-for-mac-and-ios-updates/",
            "updated": 1520915769,
            "site_name": "Eternal Storms Software Blog"
        },
        {
            "id": "https://blog.eternalstorms.at/?p=1472",
            "title": "Yoink 3.4.1 improves stability, compatibility with apps",
            "link": "https://blog.eternalstorms.at/2018/02/09/yoink-3-4-1-improves-stability-compatibility-with-apps/",
            "updated": 1518154445,
            "site_name": "Eternal Storms Software Blog"
        },
        {
            "id": "https://blog.eternalstorms.at/?p=1462",
            "title": "Yoink v1.1 for iPad and iPhone now available",
            "link": "https://blog.eternalstorms.at/2017/12/07/yoink-v1-1-for-ipad-and-iphone-now-available/",
            "updated": 1512634412,
            "site_name": "Eternal Storms Software Blog"
        },
        {
            "id": "https://blog.eternalstorms.at/?p=1455",
            "title": "Thoughts on App Review",
            "link": "https://blog.eternalstorms.at/2017/10/13/thoughts-on-app-review/",
            "updated": 1507889941,
            "site_name": "Eternal Storms Software Blog"
        },
        {
            "id": "https://blog.eternalstorms.at/?p=1449",
            "title": "Yoink for iPad and iPhone now available \u2013 Improve and Simplify Drag and Drop",
            "link": "https://blog.eternalstorms.at/2017/10/12/yoink-for-ipad-and-iphone-now-available-improve-and-simplify-drag-and-drop/",
            "updated": 1507782884,
            "site_name": "Eternal Storms Software Blog"
        },
        {
            "id": "https://blog.eternalstorms.at/?p=1445",
            "title": "Fix for Yoink 3.4\u2019s PopClip Integration",
            "link": "https://blog.eternalstorms.at/2017/10/03/fix-for-yoink-3-4s-popclip-integration/",
            "updated": 1507013295,
            "site_name": "Eternal Storms Software Blog"
        },
        {
            "id": "https://eternalstorms.wordpress.com/?p=1430",
            "title": "Detecting favicons in Yoink v3.3",
            "link": "https://blog.eternalstorms.at/2017/07/03/detecting-favicons-in-yoink-v3-3/",
            "updated": 1499059198,
            "site_name": "Eternal Storms Software Blog"
        },
        {
            "id": "https://eternalstorms.wordpress.com/?p=1420",
            "title": "Yoink 3.3 adds \u201cFile Recall\u201d, Better Sharing Tools and More",
            "link": "https://blog.eternalstorms.at/2017/06/29/yoink-3-3-adds-file-recall-better-sharing-tools-and-more/",
            "updated": 1498732353,
            "site_name": "Eternal Storms Software Blog"
        },
        {
            "id": "https://eternalstorms.wordpress.com/?p=1406",
            "title": "What I\u2026 (February, March 2017)",
            "link": "https://blog.eternalstorms.at/2017/03/30/what-i-february-march-2017/",
            "updated": 1490865474,
            "site_name": "Eternal Storms Software Blog"
        },
        {
            "id": "https://eternalstorms.wordpress.com/?p=1358",
            "title": "Mac Developer Tip: Programmatically Starting a Search on the Mac App Store",
            "link": "https://blog.eternalstorms.at/2017/02/13/mac-developer-tip-programmatically-starting-a-search-on-the-mac-app-store/",
            "updated": 1486982269,
            "site_name": "Eternal Storms Software Blog"
        },
        {
            "id": "https://eternalstorms.wordpress.com/?p=1351",
            "title": "Mac Developer Tip: NSTouchBar in a Share Extension",
            "link": "https://blog.eternalstorms.at/2017/02/08/mac-developer-tip-nstouchbar-in-a-share-extension/",
            "updated": 1486551880,
            "site_name": "Eternal Storms Software Blog"
        },
        {
            "id": "https://eternalstorms.wordpress.com/?p=1340",
            "title": "What I\u2026 (November 2016 \u2013 January 2017)",
            "link": "https://blog.eternalstorms.at/2017/02/06/what-i-november-2016-january-2017/",
            "updated": 1486380349,
            "site_name": "Eternal Storms Software Blog"
        },
        {
            "id": "https://eternalstorms.wordpress.com/?p=1317",
            "title": "#BlackFriday Deals at Eternal Storms Software",
            "link": "https://blog.eternalstorms.at/2016/11/25/blackfriday-deals-at-eternal-storms-software/",
            "updated": 1480061015,
            "site_name": "Eternal Storms Software Blog"
        },
        {
            "id": "https://eternalstorms.wordpress.com/?p=1285",
            "title": "Glimpses 2.2 adds Touch Bar Support",
            "link": "https://blog.eternalstorms.at/2016/11/14/glimpses-2-2-adds-touch-bar-support/",
            "updated": 1479111264,
            "site_name": "Eternal Storms Software Blog"
        },
        {
            "id": "https://eternalstorms.wordpress.com/?p=1278",
            "title": "Yoink on Sale \u2013 72% off",
            "link": "https://blog.eternalstorms.at/2016/11/08/yoink-on-sale-72-off/",
            "updated": 1478596909,
            "site_name": "Eternal Storms Software Blog"
        },
        {
            "id": "https://eternalstorms.wordpress.com/?p=1220",
            "title": "iTunes Affiliate Program \u2013 One Year In",
            "link": "https://blog.eternalstorms.at/2016/11/01/itunes-affiliate-program-one-year-in/",
            "updated": 1477990064,
            "site_name": "Eternal Storms Software Blog"
        },
        {
            "id": "https://eternalstorms.wordpress.com/?p=1246",
            "title": "What I.. (October 2016)",
            "link": "https://blog.eternalstorms.at/2016/10/31/what-i-october-2016/",
            "updated": 1477905725,
            "site_name": "Eternal Storms Software Blog"
        },
        {
            "id": "https://eternalstorms.wordpress.com/?p=1205",
            "title": "How to Badge an App\u2019s Icon in the Dock",
            "link": "https://blog.eternalstorms.at/2016/10/29/how-to-badge-an-apps-icon-in-the-dock/",
            "updated": 1477739480,
            "site_name": "Eternal Storms Software Blog"
        },
        {
            "id": "https://eternalstorms.wordpress.com/?p=1196",
            "title": "Follow-Up: Inactive Checkboxes Are Poor UX",
            "link": "https://blog.eternalstorms.at/2016/10/27/follow-up-inactive-checkboxes-are-poor-ux/",
            "updated": 1477539657,
            "site_name": "Eternal Storms Software Blog"
        },
        {
            "id": "https://eternalstorms.wordpress.com/?p=1191",
            "title": "Yoink v3.2.5 Improves Compatibility with macOS Sierra",
            "link": "https://blog.eternalstorms.at/2016/10/26/yoink-v3-2-5-improves-compatibility-with-macos-sierra/",
            "updated": 1477458924,
            "site_name": "Eternal Storms Software Blog"
        },
        {
            "id": "https://eternalstorms.wordpress.com/?p=1181",
            "title": "Yoink\u2019s Revenue a Month After Localizing",
            "link": "https://blog.eternalstorms.at/2016/10/21/yoinks-revenue-a-month-after-localizing/",
            "updated": 1477053006,
            "site_name": "Eternal Storms Software Blog"
        },
        {
            "id": "https://eternalstorms.wordpress.com/?p=1138",
            "title": "What I\u2026 (September 2016)",
            "link": "https://blog.eternalstorms.at/2016/10/10/what-i-september-2016/",
            "updated": 1476097627,
            "site_name": "Eternal Storms Software Blog"
        },
        {
            "id": "https://eternalstorms.wordpress.com/?p=1110",
            "title": "Guest Blog Post: The Story Behind Claquette \u2013 Animated Screenshots",
            "link": "https://blog.eternalstorms.at/2016/09/28/guest-blog-post-the-story-behind-claquette-animated-screenshots/",
            "updated": 1475067517,
            "site_name": "Eternal Storms Software Blog"
        },
        {
            "id": "https://eternalstorms.wordpress.com/?p=1040",
            "title": "Deconstructing and Reimplementing macOS\u2019 screencapture CLI",
            "link": "https://blog.eternalstorms.at/2016/09/10/deconstructing-and-reimplementing-macos-screencapture-cli/",
            "updated": 1473512490,
            "site_name": "Eternal Storms Software Blog"
        },
        {
            "id": "https://eternalstorms.wordpress.com/?p=1022",
            "title": "ScreenFloat now works on macOS Sierra",
            "link": "https://blog.eternalstorms.at/2016/09/07/screenfloat-now-works-on-macos-sierra/",
            "updated": 1473249671,
            "site_name": "Eternal Storms Software Blog"
        },
        {
            "id": "https://eternalstorms.wordpress.com/?p=954",
            "title": "What I\u2026 (August 2016)",
            "link": "https://blog.eternalstorms.at/2016/09/06/what-i-august-2016/",
            "updated": 1473150546,
            "site_name": "Eternal Storms Software Blog"
        },
        {
            "id": "https://eternalstorms.wordpress.com/?p=921",
            "title": "Glimpses v2.1 released \u2013 Your Still Motion Video Creator for Mac",
            "link": "https://blog.eternalstorms.at/2016/08/15/glimpses-v2-1-released-your-still-motion-video-creator-for-mac/",
            "updated": 1471220144,
            "site_name": "Eternal Storms Software Blog"
        },
        {
            "id": "https://eternalstorms.wordpress.com/?p=926",
            "title": "Inactive Checkboxes are Poor UX",
            "link": "https://blog.eternalstorms.at/2016/08/12/inactive-checkboxes-are-poor-ux/",
            "updated": 1471009632,
            "site_name": "Eternal Storms Software Blog"
        },
        {
            "id": "https://eternalstorms.wordpress.com/?p=892",
            "title": "What I\u2026 (July 2016)",
            "link": "https://blog.eternalstorms.at/2016/08/05/what-i-july-2016/",
            "updated": 1470371156,
            "site_name": "Eternal Storms Software Blog"
        },
        {
            "id": "https://eternalstorms.wordpress.com/?p=874",
            "title": "screencapture and the Sandbox in macOS Sierra (Updated)",
            "link": "https://blog.eternalstorms.at/2016/08/01/screencapture-and-the-sandbox-in-macos-sierra/",
            "updated": 1470021233,
            "site_name": "Eternal Storms Software Blog"
        },
        {
            "id": "https://eternalstorms.wordpress.com/?p=864",
            "title": "What I\u2026 (June 2016)",
            "link": "https://blog.eternalstorms.at/2016/07/12/what-i-june-2016/",
            "updated": 1468318136,
            "site_name": "Eternal Storms Software Blog"
        },
        {
            "id": "https://eternalstorms.wordpress.com/?p=852",
            "title": "What I\u2026 (May 2016)",
            "link": "https://blog.eternalstorms.at/2016/05/31/what-i-may-2016/",
            "updated": 1464699674,
            "site_name": "Eternal Storms Software Blog"
        },
        {
            "id": "https://eternalstorms.wordpress.com/?p=843",
            "title": "SiriMote 1.2 Released \u2013 Control your Mac with your Apple TV Remote",
            "link": "https://blog.eternalstorms.at/2016/05/18/sirimote-1-2-released-control-your-mac-with-your-apple-tv-remote/",
            "updated": 1463562596,
            "site_name": "Eternal Storms Software Blog"
        },
        {
            "id": "https://eternalstorms.wordpress.com/?p=830",
            "title": "What I\u2026 (April 2016)",
            "link": "https://blog.eternalstorms.at/2016/05/02/what-i-april-2016/",
            "updated": 1462152061,
            "site_name": "Eternal Storms Software Blog"
        },
        {
            "id": "https://eternalstorms.wordpress.com/?p=789",
            "title": "Yoink 3.2 adds Force Touch Support and more",
            "link": "https://blog.eternalstorms.at/2016/04/27/yoink-3-2-adds-force-touch-support-and-more/",
            "updated": 1461724686,
            "site_name": "Eternal Storms Software Blog"
        },
        {
            "id": "https://eternalstorms.wordpress.com/?p=799",
            "title": "Developer Tip: How to Install the Ink System Preferences Pane Without a Graphics Tablet",
            "link": "https://blog.eternalstorms.at/2016/04/22/developer-tip-how-to-install-the-ink-system-preferences-pane-without-a-graphics-tablet/",
            "updated": 1461302282,
            "site_name": "Eternal Storms Software Blog"
        },
        {
            "id": "https://eternalstorms.wordpress.com/?p=772",
            "title": "Under-The-Hood Improvements in Yoink 3.2",
            "link": "https://blog.eternalstorms.at/2016/04/11/under-the-hood-improvements-in-yoink-3-2/",
            "updated": 1460366301,
            "site_name": "Eternal Storms Software Blog"
        },
        {
            "id": "https://eternalstorms.wordpress.com/?p=762",
            "title": "What I\u2026 (March 2016)",
            "link": "https://blog.eternalstorms.at/2016/03/31/what-i-march-2016/",
            "updated": 1459431992,
            "site_name": "Eternal Storms Software Blog"
        },
        {
            "id": "https://eternalstorms.wordpress.com/?p=750",
            "title": "Mac Developer Tip: How to Simulate Memory Pressure",
            "link": "https://blog.eternalstorms.at/2016/03/31/mac-developer-tip-how-to-simulate-memory-pressure/",
            "updated": 1459422391,
            "site_name": "Eternal Storms Software Blog"
        },
        {
            "id": "https://eternalstorms.wordpress.com/?p=747",
            "title": "Opinion: Why the iPhone SE Should Have 3D Touch",
            "link": "https://blog.eternalstorms.at/2016/03/23/opinion-why-the-iphone-se-should-have-3d-touch/",
            "updated": 1458719812,
            "site_name": "Eternal Storms Software Blog"
        },
        {
            "id": "https://eternalstorms.wordpress.com/?p=708",
            "title": "What I\u2026 (February 2016)",
            "link": "https://blog.eternalstorms.at/2016/03/05/what-i-february-2016/",
            "updated": 1457181018,
            "site_name": "Eternal Storms Software Blog"
        },
        {
            "id": "https://eternalstorms.wordpress.com/?p=683",
            "title": "What I\u2026 (December \u201915, January \u201916)",
            "link": "https://blog.eternalstorms.at/2016/02/02/what-i-december-15-january-16/",
            "updated": 1454421666,
            "site_name": "Eternal Storms Software Blog"
        },
        {
            "id": "https://eternalstorms.wordpress.com/?p=639",
            "title": "Post-Mortem: The Mac App Store\u2019s Get Productive Promotion",
            "link": "https://blog.eternalstorms.at/2016/02/01/post-mortem-the-mac-app-stores-get-productive-promotion/",
            "updated": 1454334431,
            "site_name": "Eternal Storms Software Blog"
        },
        {
            "id": "https://eternalstorms.wordpress.com/?p=626",
            "title": "Get Productive \u2013 Mac App Store Promotion",
            "link": "https://blog.eternalstorms.at/2016/01/21/get-productive-mac-app-store-promotion/",
            "updated": 1453387176,
            "site_name": "Eternal Storms Software Blog"
        },
        {
            "id": "https://eternalstorms.wordpress.com/?p=619",
            "title": "Yoink Automator Workflow: Add Last Saved File to Yoink",
            "link": "https://blog.eternalstorms.at/2016/01/12/yoink-automator-workflow-add-last-saved-file-to-yoink/",
            "updated": 1452603028,
            "site_name": "Eternal Storms Software Blog"
        },
        {
            "id": "https://eternalstorms.wordpress.com/?p=614",
            "title": "What I\u2026 (November 2015)",
            "link": "https://blog.eternalstorms.at/2015/12/02/what-i-november-2015/",
            "updated": 1449035013,
            "site_name": "Eternal Storms Software Blog"
        },
        {
            "id": "https://eternalstorms.wordpress.com/?p=597",
            "title": "SiriMote \u2013 Control your Mac with your Apple TV Siri Remote",
            "link": "https://blog.eternalstorms.at/2015/12/01/sirimote-control-your-mac-with-your-apple-tv-siri-remote/",
            "updated": 1448977940,
            "site_name": "Eternal Storms Software Blog"
        },
        {
            "id": "https://eternalstorms.wordpress.com/?p=593",
            "title": "Black Friday Sale 2015",
            "link": "https://blog.eternalstorms.at/2015/11/27/black-friday-sale-2015/",
            "updated": 1448615760,
            "site_name": "Eternal Storms Software Blog"
        },
        {
            "id": "https://eternalstorms.wordpress.com/?p=583",
            "title": "How To: Detect Force Touch-Capable Devices on the Mac",
            "link": "https://blog.eternalstorms.at/2015/11/16/how-to-detect-force-touch-capable-devices-on-the-mac/",
            "updated": 1447675675,
            "site_name": "Eternal Storms Software Blog"
        },
        {
            "id": "https://eternalstorms.wordpress.com/?p=573",
            "title": "What I\u2026 (October 2015)",
            "link": "https://blog.eternalstorms.at/2015/11/04/what-i-october-2015/",
            "updated": 1446646622,
            "site_name": "Eternal Storms Software Blog"
        },
        {
            "id": "https://eternalstorms.wordpress.com/?p=551",
            "title": "How To Receive Force Touch Events from an NSTableView",
            "link": "https://blog.eternalstorms.at/2015/10/24/how-to-receive-force-touch-events-from-an-nstableview/",
            "updated": 1445668654,
            "site_name": "Eternal Storms Software Blog"
        },
        {
            "id": "https://eternalstorms.wordpress.com/?p=540",
            "title": "Pair the Apple TV Developer Kit Siri Remote with Xcode\u2019s Simulator (Updated October 6th, 2015)",
            "link": "https://blog.eternalstorms.at/2015/10/05/pair-the-apple-tv-developer-kit-siri-remote-with-xcodes-simulator/",
            "updated": 1444035352,
            "site_name": "Eternal Storms Software Blog"
        },
        {
            "id": "https://eternalstorms.wordpress.com/?p=534",
            "title": "What I\u2026 (September 2015)",
            "link": "https://blog.eternalstorms.at/2015/09/30/what-i-september-2015/",
            "updated": 1443608718,
            "site_name": "Eternal Storms Software Blog"
        },
        {
            "id": "https://eternalstorms.wordpress.com/?p=523",
            "title": "OS X 10.11 El Capitan Compatibility",
            "link": "https://blog.eternalstorms.at/2015/09/29/os-x-10-11-el-capitan-compatibility/",
            "updated": 1443521188,
            "site_name": "Eternal Storms Software Blog"
        },
        {
            "id": "https://eternalstorms.wordpress.com/?p=513",
            "title": "Yoink Update 3.1 \u2013 Simplify Drag and Drop on your Mac",
            "link": "https://blog.eternalstorms.at/2015/09/03/yoink-update-3-1-simplify-drag-and-drop-on-your-mac/",
            "updated": 1441276304,
            "site_name": "Eternal Storms Software Blog"
        },
        {
            "id": "https://eternalstorms.wordpress.com/?p=507",
            "title": "Yoink Workflow \u2013 Quickly Add Mail Attachments",
            "link": "https://blog.eternalstorms.at/2015/09/02/yoink-workflow-quickly-add-mail-attachments/",
            "updated": 1441186193,
            "site_name": "Eternal Storms Software Blog"
        },
        {
            "id": "https://eternalstorms.wordpress.com/?p=496",
            "title": "What I\u2026 (August 2015)",
            "link": "https://blog.eternalstorms.at/2015/09/01/what-i-august-2015/",
            "updated": 1441087189,
            "site_name": "Eternal Storms Software Blog"
        },
        {
            "id": "https://eternalstorms.wordpress.com/?p=476",
            "title": "Guest Blog Post: The Story Behind Gestimer",
            "link": "https://blog.eternalstorms.at/2015/08/14/guest-blog-post-the-story-behind-gestimer/",
            "updated": 1439524652,
            "site_name": "Eternal Storms Software Blog"
        },
        {
            "id": "https://eternalstorms.wordpress.com/?p=472",
            "title": "What I\u2026 (July 2015)",
            "link": "https://blog.eternalstorms.at/2015/07/31/what-i-july-2015/",
            "updated": 1438314468,
            "site_name": "Eternal Storms Software Blog"
        },
        {
            "id": "https://eternalstorms.wordpress.com/?p=457",
            "title": "Security-Scoped NSURL bookmarks and Safari\u2019s webarchive files",
            "link": "https://blog.eternalstorms.at/2015/07/10/security-scoped-nsurl-bookmarks-and-safaris-webarchive-files/",
            "updated": 1436526755,
            "site_name": "Eternal Storms Software Blog"
        },
        {
            "id": "https://eternalstorms.wordpress.com/?p=447",
            "title": "What I\u2026 (June 2015)",
            "link": "https://blog.eternalstorms.at/2015/07/02/what-i-june-2015/",
            "updated": 1435819924,
            "site_name": "Eternal Storms Software Blog"
        },
        {
            "id": "https://eternalstorms.wordpress.com/?p=431",
            "title": "Guest Blog Post: The Story Behind Review Times",
            "link": "https://blog.eternalstorms.at/2015/06/10/guest-blog-post-the-story-behind-review-times/",
            "updated": 1433923223,
            "site_name": "Eternal Storms Software Blog"
        },
        {
            "id": "https://eternalstorms.wordpress.com/?p=423",
            "title": "Introducing Glimpses for Mac \u2013 turn your photos and music into stunning Still Motion videos",
            "link": "https://blog.eternalstorms.at/2015/06/08/introducing-glimpses-for-mac-turn-your-photos-and-music-into-stunning-still-motion-videos/",
            "updated": 1433731224,
            "site_name": "Eternal Storms Software Blog"
        },
        {
            "id": "https://eternalstorms.wordpress.com/?p=416",
            "title": "What I\u2026 (May 2015)",
            "link": "https://blog.eternalstorms.at/2015/06/02/what-i-may-2015/",
            "updated": 1433220266,
            "site_name": "Eternal Storms Software Blog"
        },
        {
            "id": "https://eternalstorms.wordpress.com/?p=406",
            "title": "How To: Animate a determinate NSProgressIndicator (Open Source)",
            "link": "https://blog.eternalstorms.at/2015/05/06/how-to-animate-a-determinate-nsprogressindicator-open-source/",
            "updated": 1430888450,
            "site_name": "Eternal Storms Software Blog"
        },
        {
            "id": "https://eternalstorms.wordpress.com/?p=376",
            "title": "What I\u2026 (April 2015)",
            "link": "https://blog.eternalstorms.at/2015/04/30/what-i-april-2015/",
            "updated": 1430350679,
            "site_name": "Eternal Storms Software Blog"
        },
        {
            "id": "https://eternalstorms.wordpress.com/?p=387",
            "title": "Zoom-Transition between NSViews",
            "link": "https://blog.eternalstorms.at/2015/04/29/opensource-zoom-transition-between-nsviews/",
            "updated": 1430237586,
            "site_name": "Eternal Storms Software Blog"
        },
        {
            "id": "https://eternalstorms.wordpress.com/?p=362",
            "title": "Website \u201cBranding\u201d",
            "link": "https://blog.eternalstorms.at/2015/04/22/website-branding/",
            "updated": 1429668729,
            "site_name": "Eternal Storms Software Blog"
        },
        {
            "id": "https://eternalstorms.wordpress.com/?p=334",
            "title": "ESSSquareProgressIndicator for iOS and OS X",
            "link": "https://blog.eternalstorms.at/2015/04/02/esssquareprogressindicator-for-ios-and-os-x/",
            "updated": 1427938229,
            "site_name": "Eternal Storms Software Blog"
        },
        {
            "id": "https://eternalstorms.wordpress.com/?p=327",
            "title": "Teespring T-Shirt Campaign \u2013 Eternal Storms Software & charity:water",
            "link": "https://blog.eternalstorms.at/2015/03/27/teespring-t-shirt-campaign-eternal-storms-software-charitywater/",
            "updated": 1427453915,
            "site_name": "Eternal Storms Software Blog"
        },
        {
            "id": "https://eternalstorms.wordpress.com/?p=319",
            "title": "When to Send a Press Release \u2013 Are Embargoes Useful?",
            "link": "https://blog.eternalstorms.at/2015/03/17/when-to-send-a-press-release-are-embargoes-useful/",
            "updated": 1426591421,
            "site_name": "Eternal Storms Software Blog"
        },
        {
            "id": "https://eternalstorms.wordpress.com/?p=317",
            "title": "Transloader 2.1 Released \u2013 Action Extension, Today Widget, Push Notifications",
            "link": "https://blog.eternalstorms.at/2015/03/10/transloader-2-1-released-action-extension-today-widget-push-notifications/",
            "updated": 1425959470,
            "site_name": "Eternal Storms Software Blog"
        },
        {
            "id": "https://eternalstorms.wordpress.com/?p=307",
            "title": "Making ZEN (Part 2)",
            "link": "https://blog.eternalstorms.at/2015/02/04/making-zen-part-2/",
            "updated": 1423033151,
            "site_name": "Eternal Storms Software Blog"
        },
        {
            "id": "https://eternalstorms.wordpress.com/?p=298",
            "title": "iOS 8 Safari Action Extension; UIWebView Zoom, Scale, Scroll Position and JavaScript",
            "link": "https://blog.eternalstorms.at/2015/01/29/ios-8-safari-action-extension-uiwebview-zoom-scale-scroll-position-and-javascript/",
            "updated": 1422505279,
            "site_name": "Eternal Storms Software Blog"
        },
        {
            "id": "https://eternalstorms.wordpress.com/?p=290",
            "title": "Transloader Action Extension (iOS 8)",
            "link": "https://blog.eternalstorms.at/2015/01/27/transloader-action-extension-ios-8/",
            "updated": 1422361306,
            "site_name": "Eternal Storms Software Blog"
        },
        {
            "id": "https://eternalstorms.wordpress.com/?p=279",
            "title": "Making ZEN (Part 1)",
            "link": "https://blog.eternalstorms.at/2015/01/26/making-zen-part-1/",
            "updated": 1422252523,
            "site_name": "Eternal Storms Software Blog"
        },
        {
            "id": "https://eternalstorms.wordpress.com/?p=263",
            "title": "Capture Selective Screenshots in Yoink with Automator (Updated October 14, 2015)",
            "link": "https://blog.eternalstorms.at/2015/01/15/capture-selective-screenshots-in-yoink/",
            "updated": 1421302496,
            "site_name": "Eternal Storms Software Blog"
        },
        {
            "id": "https://eternalstorms.wordpress.com/?p=257",
            "title": "\u201cNew Year, New You\u201d \u2013 Apple includes Yoink in a Mac App Store feature",
            "link": "https://blog.eternalstorms.at/2015/01/07/new-year-new-you-apple-includes-yoink-in-a-mac-app-store-feature/",
            "updated": 1420598955,
            "site_name": "Eternal Storms Software Blog"
        },
        {
            "id": "https://eternalstorms.wordpress.com/?p=253",
            "title": "Using Yoink from the Terminal on OS X",
            "link": "https://blog.eternalstorms.at/2014/12/18/using-yoink-from-the-terminal-on-os-x/",
            "updated": 1418879048,
            "site_name": "Eternal Storms Software Blog"
        },
        {
            "id": "http://eternalstorms.wordpress.com/?p=250",
            "title": "Yoink 3 Preview",
            "link": "https://blog.eternalstorms.at/2014/11/07/yoink-3-preview/",
            "updated": 1415349016,
            "site_name": "Eternal Storms Software Blog"
        },
        {
            "id": "http://eternalstorms.wordpress.com/?p=244",
            "title": "Upcoming Changes for Transloader on iOS 8",
            "link": "https://blog.eternalstorms.at/2014/09/24/upcoming-changes-for-transloader-on-ios-8/",
            "updated": 1411565483,
            "site_name": "Eternal Storms Software Blog"
        },
        {
            "id": "http://eternalstorms.wordpress.com/?p=241",
            "title": "iCloud Documents & Data in OS X Yosemite and iOS 8",
            "link": "https://blog.eternalstorms.at/2014/09/17/icloud-documents-data-in-os-x-yosemite-and-ios-8/",
            "updated": 1410941707,
            "site_name": "Eternal Storms Software Blog"
        },
        {
            "id": "http://eternalstorms.wordpress.com/?p=236",
            "title": "Contacting customers through the App Store",
            "link": "https://blog.eternalstorms.at/2014/08/13/contacting-customers-through-the-app-store/",
            "updated": 1407914159,
            "site_name": "Eternal Storms Software Blog"
        },
        {
            "id": "http://eternalstorms.wordpress.com/?p=234",
            "title": "Developing flickery 2.0 \u2013 Part 2: Upload",
            "link": "https://blog.eternalstorms.at/2014/04/03/developing-flickery-2-0-part-2-upload/",
            "updated": 1396532968,
            "site_name": "Eternal Storms Software Blog"
        },
        {
            "id": "https://eternalstorms.wordpress.com/?p=224",
            "title": "Developing flickery 2.0 \u2013 Part 1: The Past",
            "link": "https://blog.eternalstorms.at/2014/02/21/developing-flickery-2-0-part-1-the-past-3/",
            "updated": 1392917770,
            "site_name": "Eternal Storms Software Blog"
        },
        {
            "id": "https://eternalstorms.wordpress.com/?p=211",
            "title": "Creating and Developing Briefly for Mac",
            "link": "https://blog.eternalstorms.at/2013/07/23/briefly-for-mac-a-post-mortem/",
            "updated": 1374551040,
            "site_name": "Eternal Storms Software Blog"
        },
        {
            "id": "https://eternalstorms.wordpress.com/?p=195",
            "title": "Proudly Introducing Briefly \u2013 Create Still Motion Videos with Ease",
            "link": "https://blog.eternalstorms.at/2013/07/03/proudly-introducing-briefly-create-still-motion-videos-with-ease/",
            "updated": 1372813431,
            "site_name": "Eternal Storms Software Blog"
        },
        {
            "id": "https://eternalstorms.wordpress.com/?p=192",
            "title": "WWDC \u201913 \u2013 Some thoughts",
            "link": "https://blog.eternalstorms.at/2013/06/11/wwdc-13-some-thoughts/",
            "updated": 1370947852,
            "site_name": "Eternal Storms Software Blog"
        },
        {
            "id": "https://eternalstorms.wordpress.com/?p=187",
            "title": "Transloader \u2013 A (pseudo) Post-Mortem",
            "link": "https://blog.eternalstorms.at/2013/01/04/on-transloader/",
            "updated": 1357278885,
            "site_name": "Eternal Storms Software Blog"
        },
        {
            "id": "https://eternalstorms.wordpress.com/?p=178",
            "title": "NSBegin*AlertSheet(\u2026) with ^Blocks",
            "link": "https://blog.eternalstorms.at/2012/10/12/nsbeginalertsheet-with-blocks/",
            "updated": 1350038187,
            "site_name": "Eternal Storms Software Blog"
        }
    ]
}