{
    "updated": 1714470949,
    "posts": [
        {
            "id": "https://smashswift.com/?p=1558",
            "title": "How To Change Picker Text Color In SwiftUI",
            "link": "https://smashswift.com/how-to-change-picker-text-color-in-swiftui/",
            "updated": 1697360880,
            "site_name": "Smash Swift"
        },
        {
            "id": "https://smashswift.com/?p=1552",
            "title": "How To Edit Navigation Title In SwiftUI",
            "link": "https://smashswift.com/how-to-edit-navigation-title-in-swiftui/",
            "updated": 1696755600,
            "site_name": "Smash Swift"
        },
        {
            "id": "https://smashswift.com/?p=1544",
            "title": "How To Iterate Array Of Objects To Create Views In SwiftUI",
            "link": "https://smashswift.com/how-to-iterate-array-of-objects-to-create-views-in-swiftui/",
            "updated": 1674349784,
            "site_name": "Smash Swift"
        },
        {
            "id": "https://smashswift.com/?p=1541",
            "title": "How To Create Decimal From Double",
            "link": "https://smashswift.com/how-to-create-decimal-from-double/",
            "updated": 1673779135,
            "site_name": "Smash Swift"
        },
        {
            "id": "https://smashswift.com/?p=1532",
            "title": "How To Change Size Of Sheet In SwiftUI",
            "link": "https://smashswift.com/how-to-change-size-of-sheet-in-swiftui/",
            "updated": 1667114254,
            "site_name": "Smash Swift"
        },
        {
            "id": "https://smashswift.com/?p=1528",
            "title": "How To Change URLSession Cache Size",
            "link": "https://smashswift.com/how-to-change-urlsession-cache-size/",
            "updated": 1661032920,
            "site_name": "Smash Swift"
        },
        {
            "id": "https://smashswift.com/?p=1522",
            "title": "How To Clear URLSession Cache",
            "link": "https://smashswift.com/how-to-clear-urlsession-cache/",
            "updated": 1645364915,
            "site_name": "Smash Swift"
        },
        {
            "id": "https://smashswift.com/?p=1512",
            "title": "How To Add Gradient To Text In SwiftUI",
            "link": "https://smashswift.com/how-to-add-gradient-to-text-in-swiftui/",
            "updated": 1644147922,
            "site_name": "Smash Swift"
        },
        {
            "id": "https://smashswift.com/?p=1504",
            "title": "How To Create Secure Input In SwiftUI",
            "link": "https://smashswift.com/how-to-create-secure-input-in-swiftui/",
            "updated": 1642911780,
            "site_name": "Smash Swift"
        },
        {
            "id": "https://smashswift.com/?p=1495",
            "title": "mikr.us \u2013 Virtual Private Server Review",
            "link": "https://smashswift.com/mikr-us-virtual-private-server-review/",
            "updated": 1641640051,
            "site_name": "Smash Swift"
        }
    ]
}